textual_router/__init__.py
textual_router/py.typed
textual_router/router.py
textual_router-0.2.3.dist-info/LICENSE
textual_router-0.2.3.dist-info/METADATA
textual_router-0.2.3.dist-info/WHEEL
textual_router-0.2.3.dist-info/RECORD
