Metadata-Version: 2.1
Name: textual-router
Version: 0.2.3
Summary: A view router for Textual projects
Home-page: https://github.com/imajacket/textual_router
License: MIT
Author: imajacket
Requires-Python: >=3.10,<4.0
Classifier: Intended Audience :: Developers
Classifier: License :: OSI Approved :: MIT License
Classifier: Operating System :: OS Independent
Classifier: Programming Language :: Python :: 3
Classifier: Programming Language :: Python :: 3.10
Classifier: Programming Language :: Python :: 3.11
Classifier: Programming Language :: Python :: 3.12
Classifier: Programming Language :: Python :: 3.13
Classifier: Typing :: Typed
Requires-Dist: textual (>=0.85.2,<0.86.0)
Project-URL: Repository, https://github.com/imajacket/textual_router
